odoo/addons/hr_employee_lastnames/README.rst
odoo/addons/hr_employee_lastnames/__init__.py
odoo/addons/hr_employee_lastnames/__manifest__.py
odoo/addons/hr_employee_lastnames/hook.py
odoo/addons/hr_employee_lastnames/i18n/es.po
odoo/addons/hr_employee_lastnames/i18n/hr_employee_lastnames.pot
odoo/addons/hr_employee_lastnames/models/__init__.py
odoo/addons/hr_employee_lastnames/models/hr_employee.py
odoo/addons/hr_employee_lastnames/readme/CONTRIBUTORS.rst
odoo/addons/hr_employee_lastnames/readme/DESCRIPTION.rst
odoo/addons/hr_employee_lastnames/readme/USAGE.rst
odoo/addons/hr_employee_lastnames/static/description/icon.png
odoo/addons/hr_employee_lastnames/static/description/index.html
odoo/addons/hr_employee_lastnames/tests/__init__.py
odoo/addons/hr_employee_lastnames/tests/test_hr_employee_lastnames.py
odoo/addons/hr_employee_lastnames/views/hr_views.xml
odoo11_addon_hr_employee_lastnames-11.0.1.0.0.99.dev4.dist-info/METADATA
odoo11_addon_hr_employee_lastnames-11.0.1.0.0.99.dev4.dist-info/WHEEL
odoo11_addon_hr_employee_lastnames-11.0.1.0.0.99.dev4.dist-info/top_level.txt
odoo11_addon_hr_employee_lastnames-11.0.1.0.0.99.dev4.dist-info/RECORD
